video_analyzer_ui/__init__.py
video_analyzer_ui/server.py
video_analyzer_ui/static/css/styles.css
video_analyzer_ui/static/js/main.js
video_analyzer_ui/templates/index.html
video_analyzer_ui-0.1.0.dist-info/METADATA
video_analyzer_ui-0.1.0.dist-info/WHEEL
video_analyzer_ui-0.1.0.dist-info/entry_points.txt
video_analyzer_ui-0.1.0.dist-info/top_level.txt
video_analyzer_ui-0.1.0.dist-info/RECORD
