Metadata-Version: 2.2
Name: video-analyzer-ui
Version: 0.1.0
Summary: Web interface for the video-analyzer tool
Author-email: Jesse White <your.email@example.com>
Project-URL: Homepage, https://github.com/username/video-analyzer-ui
Project-URL: Bug Tracker, https://github.com/username/video-analyzer-ui/issues
Classifier: Programming Language :: Python :: 3
Classifier: License :: OSI Approved :: Apache Software License
Classifier: Operating System :: OS Independent
Classifier: Environment :: Web Environment
Classifier: Framework :: Flask
Requires-Python: >=3.8
Requires-Dist: flask>=3.0.0
Requires-Dist: video-analyzer>=0.1.0
Requires-Dist: werkzeug>=3.0.0
